basic_notion/__init__.py
basic_notion/attr.py
basic_notion/base.py
basic_notion/block.py
basic_notion/database.py
basic_notion/exc.py
basic_notion/field.py
basic_notion/filter.py
basic_notion/page.py
basic_notion/parent.py
basic_notion/property.py
basic_notion/property_schema.py
basic_notion/py.typed
basic_notion/query.py
basic_notion/schema.py
basic_notion/sort.py
basic_notion/titled_page.py
basic_notion/utils.py
basic_notion-0.6.2.dist-info/LICENSE
basic_notion-0.6.2.dist-info/METADATA
basic_notion-0.6.2.dist-info/WHEEL
basic_notion-0.6.2.dist-info/top_level.txt
basic_notion-0.6.2.dist-info/RECORD
