Metadata-Version: 2.1
Name: basic-notion
Version: 0.6.2
Summary: Client-agnostic model wrapper for Notion API
Home-page: https://github.com/altvod/basic-notion
Author: Grigory Statsenko
Author-email: grisha100@gmail.com
Project-URL: Bug Tracker, https://github.com/altvod/basic-notion/issues
Keywords: notion,notion-api,models
Classifier: Development Status :: 3 - Alpha
Classifier: Intended Audience :: Developers
Classifier: Topic :: Database
Classifier: Topic :: Software Development :: Libraries :: Python Modules
Classifier: Programming Language :: Python :: 3
Classifier: Programming Language :: Python :: 3 :: Only
Classifier: Programming Language :: Python :: 3.9
Classifier: Programming Language :: Python :: 3.10
Classifier: License :: OSI Approved :: MIT License
Classifier: Operating System :: OS Independent
Requires-Python: >=3.9
License-File: LICENSE
Requires-Dist: attrs
Requires-Dist: ciso8601
Provides-Extra: build
Requires-Dist: build ; extra == 'build'
Requires-Dist: twine ; extra == 'build'
Provides-Extra: testing
Requires-Dist: mypy ; extra == 'testing'
Requires-Dist: pytest ; extra == 'testing'
Requires-Dist: pytest-envfiles ; extra == 'testing'
Requires-Dist: notion-client ; extra == 'testing'
